santa_helpers/__init__.py
santa_helpers/distances.py
santa_helpers/neighbors.py
santa_helpers/parse.py
santa_helpers/paths.py
santa_helpers-0.0.2.dist-info/LICENSE
santa_helpers-0.0.2.dist-info/METADATA
santa_helpers-0.0.2.dist-info/WHEEL
santa_helpers-0.0.2.dist-info/top_level.txt
santa_helpers-0.0.2.dist-info/RECORD
