Metadata-Version: 2.1
Name: santa_helpers
Version: 0.0.2
Summary: Helpers for Advent of Codee
Home-page: https://github.com/lenarother/santa_helpers
Author: Magdalena Rother
Author-email: rother.magdalena@gmail.com
License: MIT license
Keywords: santa_helpers
Platform: UNKNOWN
Classifier: Development Status :: 2 - Pre-Alpha
Classifier: Intended Audience :: Developers
Classifier: License :: OSI Approved :: MIT License
Classifier: Natural Language :: English
Classifier: Programming Language :: Python :: 3
Classifier: Programming Language :: Python :: 3.6
Classifier: Programming Language :: Python :: 3.7
Classifier: Programming Language :: Python :: 3.8
Requires-Python: >=3.6
License-File: LICENSE
